{
 "custom_fields": [],
 "custom_perms": [],
 "doctype": "Product Family Table",
 "property_setters": [
  {
   "_assign": null,
   "_comments": null,
   "_liked_by": null,
   "_user_tags": null,
   "creation": "2019-04-18 09:07:19.103168",
   "default_value": null,
   "doc_type": "Product Family Table",
   "docstatus": 0,
   "doctype_or_field": "DocField",
   "field_name": "product_family",
   "idx": 0,
   "modified": "2019-04-18 09:07:19.103168",
   "modified_by": "Administrator",
   "name": "Product Family Table-product_family-in_list_view",
   "owner": "Administrator",
   "parent": null,
   "parentfield": null,
   "parenttype": null,
   "property": "in_list_view",
   "property_type": "Check",
   "value": "1"
  },
  {
   "_assign": null,
   "_comments": null,
   "_liked_by": null,
   "_user_tags": null,
   "creation": "2019-04-18 09:07:19.071757",
   "default_value": null,
   "doc_type": "Product Family Table",
   "docstatus": 0,
   "doctype_or_field": "DocType",
   "field_name": null,
   "idx": 0,
   "modified": "2019-04-18 09:07:19.071757",
   "modified_by": "Administrator",
   "name": "Product Family Table-read_only_onload",
   "owner": "Administrator",
   "parent": null,
   "parentfield": null,
   "parenttype": null,
   "property": "read_only_onload",
   "property_type": "Check",
   "value": null
  }
 ],
 "sync_on_migrate": 1
}