{
 "custom_fields": [
  {
   "_assign": null,
   "_comments": null,
   "_liked_by": null,
   "_user_tags": null,
   "allow_on_submit": 0,
   "bold": 0,
   "collapsible": 0,
   "collapsible_depends_on": null,
   "columns": 0,
   "creation": "2020-10-16 11:28:05.301446",
   "default": null,
   "depends_on": null,
   "description": null,
   "docstatus": 0,
   "dt": "Return Material Authorization",
   "fetch_from": null,
   "fetch_if_empty": 0,
   "fieldname": "return_notes",
   "fieldtype": "Small Text",
   "hidden": 0,
   "idx": 17,
   "ignore_user_permissions": 0,
   "ignore_xss_filter": 0,
   "in_global_search": 0,
   "in_list_view": 0,
   "in_standard_filter": 0,
   "insert_after": "return_instructions",
   "label": "Return Notes",
   "modified": "2020-10-16 11:28:05.301446",
   "modified_by": "ghyam@sea-fire.co.uk",
   "name": "Return Material Authorization-return_notes",
   "no_copy": 0,
   "options": null,
   "owner": "ghyam@sea-fire.co.uk",
   "parent": null,
   "parentfield": null,
   "parenttype": null,
   "permlevel": 0,
   "precision": "",
   "print_hide": 0,
   "print_hide_if_no_value": 0,
   "print_width": null,
   "read_only": 0,
   "report_hide": 0,
   "reqd": 0,
   "search_index": 0,
   "translatable": 1,
   "unique": 0,
   "width": null
  },
  {
   "_assign": null,
   "_comments": null,
   "_liked_by": null,
   "_user_tags": null,
   "allow_on_submit": 1,
   "bold": 0,
   "collapsible": 0,
   "collapsible_depends_on": null,
   "columns": 0,
   "creation": "2019-02-13 09:58:04.215658",
   "default": null,
   "depends_on": null,
   "description": null,
   "docstatus": 0,
   "dt": "Return Material Authorization",
   "fetch_from": null,
   "fetch_if_empty": 0,
   "fieldname": "workflow_state",
   "fieldtype": "Link",
   "hidden": 1,
   "idx": 1,
   "ignore_user_permissions": 0,
   "ignore_xss_filter": 0,
   "in_global_search": 0,
   "in_list_view": 0,
   "in_standard_filter": 0,
   "insert_after": null,
   "label": "Workflow State",
   "modified": "2019-08-16 10:29:45.727119",
   "modified_by": "Administrator",
   "name": "Return Material Authorization-workflow_state",
   "no_copy": 1,
   "options": "Workflow State",
   "owner": "Administrator",
   "parent": null,
   "parentfield": null,
   "parenttype": null,
   "permlevel": 0,
   "precision": "",
   "print_hide": 0,
   "print_hide_if_no_value": 0,
   "print_width": null,
   "read_only": 0,
   "report_hide": 0,
   "reqd": 0,
   "search_index": 0,
   "translatable": 0,
   "unique": 0,
   "width": null
  },
  {
   "_assign": null,
   "_comments": null,
   "_liked_by": null,
   "_user_tags": null,
   "allow_on_submit": 0,
   "bold": 0,
   "collapsible": 0,
   "collapsible_depends_on": null,
   "columns": 0,
   "creation": "2019-08-07 17:37:43.305488",
   "default": null,
   "depends_on": null,
   "description": null,
   "docstatus": 0,
   "dt": "Return Material Authorization",
   "fetch_from": null,
   "fetch_if_empty": 0,
   "fieldname": "return_freight_cost",
   "fieldtype": "Data",
   "hidden": 0,
   "idx": 18,
   "ignore_user_permissions": 0,
   "ignore_xss_filter": 0,
   "in_global_search": 0,
   "in_list_view": 0,
   "in_standard_filter": 0,
   "insert_after": "return_notes",
   "label": "Return Freight Cost",
   "modified": "2019-08-16 10:29:45.191384",
   "modified_by": "Administrator",
   "name": "Return Material Authorization-return_freight_cost",
   "no_copy": 0,
   "options": null,
   "owner": "Administrator",
   "parent": null,
   "parentfield": null,
   "parenttype": null,
   "permlevel": 0,
   "precision": null,
   "print_hide": 0,
   "print_hide_if_no_value": 0,
   "print_width": null,
   "read_only": 0,
   "report_hide": 0,
   "reqd": 0,
   "search_index": 0,
   "translatable": 1,
   "unique": 0,
   "width": null
  },
  {
   "_assign": null,
   "_comments": null,
   "_liked_by": null,
   "_user_tags": null,
   "allow_on_submit": 0,
   "bold": 0,
   "collapsible": 0,
   "collapsible_depends_on": null,
   "columns": 0,
   "creation": "2019-08-07 17:37:43.146689",
   "default": null,
   "depends_on": null,
   "description": null,
   "docstatus": 0,
   "dt": "Return Material Authorization",
   "fetch_from": null,
   "fetch_if_empty": 0,
   "fieldname": "purchase_order",
   "fieldtype": "Link",
   "hidden": 0,
   "idx": 54,
   "ignore_user_permissions": 0,
   "ignore_xss_filter": 0,
   "in_global_search": 0,
   "in_list_view": 0,
   "in_standard_filter": 0,
   "insert_after": "sales_order",
   "label": "Purchase Order",
   "modified": "2019-08-16 10:29:45.067468",
   "modified_by": "Administrator",
   "name": "Return Material Authorization-purchase_order",
   "no_copy": 0,
   "options": "Purchase Order",
   "owner": "Administrator",
   "parent": null,
   "parentfield": null,
   "parenttype": null,
   "permlevel": 0,
   "precision": null,
   "print_hide": 0,
   "print_hide_if_no_value": 0,
   "print_width": null,
   "read_only": 0,
   "report_hide": 0,
   "reqd": 0,
   "search_index": 0,
   "translatable": 0,
   "unique": 0,
   "width": null
  },
  {
   "_assign": null,
   "_comments": null,
   "_liked_by": null,
   "_user_tags": null,
   "allow_on_submit": 0,
   "bold": 0,
   "collapsible": 0,
   "collapsible_depends_on": null,
   "columns": 0,
   "creation": "2019-08-07 17:37:42.973518",
   "default": null,
   "depends_on": null,
   "description": null,
   "docstatus": 0,
   "dt": "Return Material Authorization",
   "fetch_from": null,
   "fetch_if_empty": 0,
   "fieldname": "rehydro",
   "fieldtype": "Check",
   "hidden": 0,
   "idx": 50,
   "ignore_user_permissions": 0,
   "ignore_xss_filter": 0,
   "in_global_search": 0,
   "in_list_view": 0,
   "in_standard_filter": 0,
   "insert_after": "cb5",
   "label": "Rehydro",
   "modified": "2019-08-16 10:29:44.957492",
   "modified_by": "Administrator",
   "name": "Return Material Authorization-rehydro",
   "no_copy": 0,
   "options": null,
   "owner": "Administrator",
   "parent": null,
   "parentfield": null,
   "parenttype": null,
   "permlevel": 0,
   "precision": null,
   "print_hide": 0,
   "print_hide_if_no_value": 0,
   "print_width": null,
   "read_only": 0,
   "report_hide": 0,
   "reqd": 0,
   "search_index": 0,
   "translatable": 0,
   "unique": 0,
   "width": null
  },
  {
   "_assign": null,
   "_comments": null,
   "_liked_by": null,
   "_user_tags": null,
   "allow_on_submit": 0,
   "bold": 0,
   "collapsible": 0,
   "collapsible_depends_on": null,
   "columns": 0,
   "creation": "2019-06-06 15:23:51.579718",
   "default": null,
   "depends_on": "eval:doc.cylinder_requalification",
   "description": null,
   "docstatus": 0,
   "dt": "Return Material Authorization",
   "fetch_from": null,
   "fetch_if_empty": 0,
   "fieldname": "test_report",
   "fieldtype": "Select",
   "hidden": 0,
   "idx": 42,
   "ignore_user_permissions": 0,
   "ignore_xss_filter": 0,
   "in_global_search": 0,
   "in_list_view": 0,
   "in_standard_filter": 0,
   "insert_after": "cylinder_date",
   "label": "Test Report",
   "modified": "2019-06-06 15:23:51.579718",
   "modified_by": "psidelinger@sea-fire.com",
   "name": "Return Material Authorization-test_report",
   "no_copy": 0,
   "options": "\nYes\nNo",
   "owner": "psidelinger@sea-fire.com",
   "parent": null,
   "parentfield": null,
   "parenttype": null,
   "permlevel": 0,
   "precision": "",
   "print_hide": 0,
   "print_hide_if_no_value": 0,
   "print_width": null,
   "read_only": 0,
   "report_hide": 0,
   "reqd": 0,
   "search_index": 0,
   "translatable": 1,
   "unique": 0,
   "width": null
  },
  {
   "_assign": null,
   "_comments": null,
   "_liked_by": null,
   "_user_tags": null,
   "allow_on_submit": 0,
   "bold": 0,
   "collapsible": 0,
   "collapsible_depends_on": null,
   "columns": 0,
   "creation": "2019-06-06 15:23:51.308869",
   "default": null,
   "depends_on": "eval:doc.cylinder_requalification",
   "description": null,
   "docstatus": 0,
   "dt": "Return Material Authorization",
   "fetch_from": null,
   "fetch_if_empty": 0,
   "fieldname": "cylinder_date",
   "fieldtype": "Date",
   "hidden": 0,
   "idx": 41,
   "ignore_user_permissions": 0,
   "ignore_xss_filter": 0,
   "in_global_search": 0,
   "in_list_view": 0,
   "in_standard_filter": 0,
   "insert_after": "cylinder_po",
   "label": "Date",
   "modified": "2019-06-06 15:23:51.308869",
   "modified_by": "psidelinger@sea-fire.com",
   "name": "Return Material Authorization-cylinder_date",
   "no_copy": 0,
   "options": null,
   "owner": "psidelinger@sea-fire.com",
   "parent": null,
   "parentfield": null,
   "parenttype": null,
   "permlevel": 0,
   "precision": "",
   "print_hide": 0,
   "print_hide_if_no_value": 0,
   "print_width": null,
   "read_only": 0,
   "report_hide": 0,
   "reqd": 0,
   "search_index": 0,
   "translatable": 0,
   "unique": 0,
   "width": null
  },
  {
   "_assign": null,
   "_comments": null,
   "_liked_by": null,
   "_user_tags": null,
   "allow_on_submit": 0,
   "bold": 0,
   "collapsible": 0,
   "collapsible_depends_on": null,
   "columns": 0,
   "creation": "2019-06-06 15:20:27.775033",
   "default": null,
   "depends_on": "eval:doc.cylinder_requalification",
   "description": null,
   "docstatus": 0,
   "dt": "Return Material Authorization",
   "fetch_from": null,
   "fetch_if_empty": 0,
   "fieldname": "cylinder_po",
   "fieldtype": "Data",
   "hidden": 0,
   "idx": 40,
   "ignore_user_permissions": 0,
   "ignore_xss_filter": 0,
   "in_global_search": 0,
   "in_list_view": 0,
   "in_standard_filter": 0,
   "insert_after": "cylinder_requalification",
   "label": "PO#",
   "modified": "2019-06-06 15:20:27.775033",
   "modified_by": "psidelinger@sea-fire.com",
   "name": "Return Material Authorization-cylinder_po",
   "no_copy": 0,
   "options": null,
   "owner": "psidelinger@sea-fire.com",
   "parent": null,
   "parentfield": null,
   "parenttype": null,
   "permlevel": 0,
   "precision": "",
   "print_hide": 0,
   "print_hide_if_no_value": 0,
   "print_width": null,
   "read_only": 0,
   "report_hide": 0,
   "reqd": 0,
   "search_index": 0,
   "translatable": 1,
   "unique": 0,
   "width": null
  },
  {
   "_assign": null,
   "_comments": null,
   "_liked_by": null,
   "_user_tags": null,
   "allow_on_submit": 0,
   "bold": 0,
   "collapsible": 0,
   "collapsible_depends_on": null,
   "columns": 0,
   "creation": "2019-06-06 15:20:26.913550",
   "default": null,
   "depends_on": null,
   "description": null,
   "docstatus": 0,
   "dt": "Return Material Authorization",
   "fetch_from": null,
   "fetch_if_empty": 0,
   "fieldname": "cylinder_requalification",
   "fieldtype": "Check",
   "hidden": 0,
   "idx": 39,
   "ignore_user_permissions": 0,
   "ignore_xss_filter": 0,
   "in_global_search": 0,
   "in_list_view": 0,
   "in_standard_filter": 0,
   "insert_after": "recommendations",
   "label": "Cylinder Requalification",
   "modified": "2019-06-06 15:20:26.913550",
   "modified_by": "psidelinger@sea-fire.com",
   "name": "Return Material Authorization-cylinder_requalification",
   "no_copy": 0,
   "options": null,
   "owner": "psidelinger@sea-fire.com",
   "parent": null,
   "parentfield": null,
   "parenttype": null,
   "permlevel": 0,
   "precision": "",
   "print_hide": 0,
   "print_hide_if_no_value": 0,
   "print_width": null,
   "read_only": 0,
   "report_hide": 0,
   "reqd": 0,
   "search_index": 0,
   "translatable": 0,
   "unique": 0,
   "width": null
  }
 ],
 "custom_perms": [
  {
   "_assign": null,
   "_comments": null,
   "_liked_by": null,
   "_user_tags": null,
   "amend": 0,
   "cancel": 0,
   "create": 1,
   "creation": "2018-12-05 15:18:11.950860",
   "delete": 1,
   "docstatus": 0,
   "email": 1,
   "export": 1,
   "idx": 1,
   "if_owner": 0,
   "import": 0,
   "modified": "2019-04-13 16:53:02.995747",
   "modified_by": "Administrator",
   "name": "37832e3360",
   "owner": "awallace@sea-fire.com",
   "parent": "Return Material Authorization",
   "parentfield": "permissions",
   "parenttype": "DocType",
   "permlevel": 0,
   "print": 1,
   "read": 1,
   "report": 1,
   "role": "System Manager",
   "set_user_permissions": 0,
   "share": 1,
   "submit": 0,
   "user_permission_doctypes": null,
   "write": 1
  },
  {
   "_assign": null,
   "_comments": null,
   "_liked_by": null,
   "_user_tags": null,
   "amend": 0,
   "cancel": 0,
   "create": 1,
   "creation": "2018-12-05 15:18:11.950860",
   "delete": 0,
   "docstatus": 0,
   "email": 1,
   "export": 1,
   "idx": 2,
   "if_owner": 0,
   "import": 0,
   "modified": "2019-04-13 16:53:03.022242",
   "modified_by": "Administrator",
   "name": "bf5b6f737a",
   "owner": "Administrator",
   "parent": "Return Material Authorization",
   "parentfield": "permissions",
   "parenttype": "DocType",
   "permlevel": 0,
   "print": 1,
   "read": 1,
   "report": 1,
   "role": "Sales User",
   "set_user_permissions": 0,
   "share": 1,
   "submit": 0,
   "user_permission_doctypes": null,
   "write": 1
  },
  {
   "_assign": null,
   "_comments": null,
   "_liked_by": null,
   "_user_tags": null,
   "amend": 0,
   "cancel": 0,
   "create": 0,
   "creation": "2018-12-05 15:18:11.950860",
   "delete": 0,
   "docstatus": 0,
   "email": 1,
   "export": 1,
   "idx": 3,
   "if_owner": 0,
   "import": 0,
   "modified": "2019-04-13 16:53:03.068243",
   "modified_by": "Administrator",
   "name": "9a39a1ff34",
   "owner": "Administrator",
   "parent": "Return Material Authorization",
   "parentfield": "permissions",
   "parenttype": "DocType",
   "permlevel": 0,
   "print": 1,
   "read": 1,
   "report": 1,
   "role": "Shipping User",
   "set_user_permissions": 0,
   "share": 1,
   "submit": 0,
   "user_permission_doctypes": null,
   "write": 1
  },
  {
   "_assign": null,
   "_comments": null,
   "_liked_by": null,
   "_user_tags": null,
   "amend": 0,
   "cancel": 0,
   "create": 0,
   "creation": "2018-12-05 15:18:11.950860",
   "delete": 0,
   "docstatus": 0,
   "email": 1,
   "export": 1,
   "idx": 4,
   "if_owner": 0,
   "import": 0,
   "modified": "2019-04-13 16:53:03.075690",
   "modified_by": "Administrator",
   "name": "d714ee40e6",
   "owner": "Administrator",
   "parent": "Return Material Authorization",
   "parentfield": "permissions",
   "parenttype": "DocType",
   "permlevel": 0,
   "print": 1,
   "read": 1,
   "report": 1,
   "role": "Internal Logistics Team Member",
   "set_user_permissions": 0,
   "share": 1,
   "submit": 0,
   "user_permission_doctypes": null,
   "write": 1
  },
  {
   "_assign": null,
   "_comments": null,
   "_liked_by": null,
   "_user_tags": null,
   "amend": 0,
   "cancel": 0,
   "create": 1,
   "creation": "2021-04-29 10:05:50.788477",
   "delete": 0,
   "docstatus": 0,
   "email": 1,
   "export": 1,
   "idx": 0,
   "if_owner": 0,
   "import": 0,
   "modified": "2021-04-29 10:05:50.788477",
   "modified_by": "ghyam@sea-fire.co.uk",
   "name": "93174680d7",
   "owner": "ghyam@sea-fire.co.uk",
   "parent": "Return Material Authorization",
   "parentfield": "permissions",
   "parenttype": "DocType",
   "permlevel": 0,
   "print": 1,
   "read": 1,
   "report": 1,
   "role": "Accounts Manager",
   "set_user_permissions": 0,
   "share": 0,
   "submit": 0,
   "user_permission_doctypes": null,
   "write": 1
  }
 ],
 "doctype": "Return Material Authorization",
 "property_setters": [
  {
   "_assign": null,
   "_comments": null,
   "_liked_by": null,
   "_user_tags": null,
   "creation": "2020-11-30 09:03:40.978741",
   "default_value": null,
   "doc_type": "Return Material Authorization",
   "docstatus": 0,
   "doctype_or_field": "DocField",
   "field_name": "customer",
   "idx": 0,
   "modified": "2020-11-30 09:03:40.978741",
   "modified_by": "ghyam@sea-fire.co.uk",
   "name": "Return Material Authorization-customer-in_standard_filter",
   "owner": "ghyam@sea-fire.co.uk",
   "parent": null,
   "parentfield": null,
   "parenttype": null,
   "property": "in_standard_filter",
   "property_type": "Check",
   "value": "1"
  },
  {
   "_assign": null,
   "_comments": null,
   "_liked_by": null,
   "_user_tags": null,
   "creation": "2020-11-30 09:03:40.962686",
   "default_value": null,
   "doc_type": "Return Material Authorization",
   "docstatus": 0,
   "doctype_or_field": "DocType",
   "field_name": null,
   "idx": 0,
   "modified": "2020-11-30 09:03:40.962686",
   "modified_by": "ghyam@sea-fire.co.uk",
   "name": "Return Material Authorization-read_only_onload",
   "owner": "ghyam@sea-fire.co.uk",
   "parent": null,
   "parentfield": null,
   "parenttype": null,
   "property": "read_only_onload",
   "property_type": "Check",
   "value": null
  },
  {
   "_assign": null,
   "_comments": null,
   "_liked_by": null,
   "_user_tags": null,
   "creation": "2020-10-16 11:49:54.125104",
   "default_value": null,
   "doc_type": "Return Material Authorization",
   "docstatus": 0,
   "doctype_or_field": "DocField",
   "field_name": "return_instructions",
   "idx": 0,
   "modified": "2020-10-16 11:49:54.125104",
   "modified_by": "ghyam@sea-fire.co.uk",
   "name": "Return Material Authorization-return_instructions-options",
   "owner": "ghyam@sea-fire.co.uk",
   "parent": null,
   "parentfield": null,
   "parenttype": null,
   "property": "options",
   "property_type": "Text",
   "value": "\nCustomer will drop-off\nCustomer will pay for return freight\nSFE will pay for return freight\nAuthorized non-return of goods\nSend to Genova Fire Service\nTo be collected by Extincteurs Nantais"
  },
  {
   "_assign": null,
   "_comments": null,
   "_liked_by": null,
   "_user_tags": null,
   "creation": "2019-12-03 13:38:23.139584",
   "default_value": null,
   "doc_type": "Return Material Authorization",
   "docstatus": 0,
   "doctype_or_field": "DocType",
   "field_name": null,
   "idx": 0,
   "modified": "2019-12-03 13:38:23.139584",
   "modified_by": "Administrator",
   "name": "Return Material Authorization-default_print_format",
   "owner": "Administrator",
   "parent": null,
   "parentfield": null,
   "parenttype": null,
   "property": "default_print_format",
   "property_type": "Data",
   "value": "SFE RMA"
  },
  {
   "_assign": null,
   "_comments": null,
   "_liked_by": null,
   "_user_tags": null,
   "creation": "2019-08-07 17:39:35.792671",
   "default_value": null,
   "doc_type": "Return Material Authorization",
   "docstatus": 0,
   "doctype_or_field": "DocField",
   "field_name": "dept",
   "idx": 0,
   "modified": "2019-08-16 10:32:15.035648",
   "modified_by": "Administrator",
   "name": "Return Material Authorization-dept-hidden",
   "owner": "Administrator",
   "parent": null,
   "parentfield": null,
   "parenttype": null,
   "property": "hidden",
   "property_type": "Check",
   "value": "1"
  },
  {
   "_assign": null,
   "_comments": null,
   "_liked_by": null,
   "_user_tags": null,
   "creation": "2019-08-07 13:40:31.518932",
   "default_value": null,
   "doc_type": "Return Material Authorization",
   "docstatus": 0,
   "doctype_or_field": "DocField",
   "field_name": "dept",
   "idx": 0,
   "modified": "2019-08-16 10:32:15.024439",
   "modified_by": "Administrator",
   "name": "Return Material Authorization-dept-default",
   "owner": "Administrator",
   "parent": null,
   "parentfield": null,
   "parenttype": null,
   "property": "default",
   "property_type": "Text",
   "value": "All Departments"
  }
 ],
 "sync_on_migrate": 1
}